README.md
setup.cfg
setup.py
grakn_protocol.egg-info/PKG-INFO
grakn_protocol.egg-info/SOURCES.txt
grakn_protocol.egg-info/dependency_links.txt
grakn_protocol.egg-info/not-zip-safe
grakn_protocol.egg-info/top_level.txt
graknprotocol/__init__.py
graknprotocol/protobuf/__init__.py
graknprotocol/protobuf/answer_pb2.py
graknprotocol/protobuf/answer_pb2_grpc.py
graknprotocol/protobuf/concept_pb2.py
graknprotocol/protobuf/concept_pb2_grpc.py
graknprotocol/protobuf/database_pb2.py
graknprotocol/protobuf/database_pb2_grpc.py
graknprotocol/protobuf/grakn_pb2.py
graknprotocol/protobuf/grakn_pb2_grpc.py
graknprotocol/protobuf/logic_pb2.py
graknprotocol/protobuf/logic_pb2_grpc.py
graknprotocol/protobuf/options_pb2.py
graknprotocol/protobuf/options_pb2_grpc.py
graknprotocol/protobuf/query_pb2.py
graknprotocol/protobuf/query_pb2_grpc.py
graknprotocol/protobuf/session_pb2.py
graknprotocol/protobuf/session_pb2_grpc.py
graknprotocol/protobuf/transaction_pb2.py
graknprotocol/protobuf/transaction_pb2_grpc.py