Metadata-Version: 2.1
Name: grakn-protocol
Version: 2.0.0a6
Summary: Grakn gRPC Protocol
Home-page: https://github.com/graknlabs/protocol/
Author: Grakn Labs
Author-email: grabl@grakn.ai
License: AGPLv3+
Keywords: grakn database graph knowledgebase knowledge-engineering
Platform: UNKNOWN
Classifier: Programming Language :: Python
Classifier: Programming Language :: Python :: 3
Classifier: Programming Language :: Python :: 3.5
Classifier: Programming Language :: Python :: 3.6
Classifier: Programming Language :: Python :: 3.7
Classifier: Programming Language :: Python :: 3.8
Classifier: License :: OSI Approved :: GNU Affero General Public License v3 or later (AGPLv3+)
Classifier: Operating System :: OS Independent
Classifier: Intended Audience :: Developers
Classifier: Intended Audience :: Science/Research
Classifier: Environment :: Console
Classifier: Topic :: Database :: Front-Ends
